{
    "homepage": "https://github.com/blacktop/ipsw",
    "description": "iOS/macOS Research Swiss Army Knife",
    "version": "3.1.234",
    "license": "MIT",
    "architecture": {
        "64bit": {
            "hash": "c61018bde486ed450078770b1564fedc417b952a919395448326da56f1809b45",
            "url": "https://github.com/blacktop/ipsw/releases/download/v3.1.234/ipsw_3.1.234_windows_x86_64.tar.gz",
            "extract_dir": "ipsw_3.1.234_windows_x86_64",
            "bin": "ipsw.exe"
        }
    },
    "checkver": "github",
    "autoupdate": {
        "architecture": {
            "64bit": {
                "url": "https://github.com/blacktop/ipsw/releases/download/v$version/ipsw_$version_windows_x86_64.tar.gz",
                "extract_dir": "ipsw_$version_windows_x86_64"
            }
        }
    }
}
