{
    "homepage": "https://github.com/rigaya/QSVEnc",
    "description": "Transcoding software using Intel Quick Sync Video.",
    "version": "7.17",
    "license": "MIT",
    "architecture": {
        "32bit": {
            "url": "https://github.com/rigaya/QSVEnc/releases/download/7.17/QSVEncC_7.17_Win32.7z",
            "hash": "8dd2477704f1bd20143adb16548d2d7c72d6f7d61e45a0ab6d4da6e5a64b4a14",
            "bin": [
                [
                    "QSVEncC.exe",
                    "qsvencc"
                ]
            ]
        },
        "64bit": {
            "url": "https://github.com/rigaya/QSVEnc/releases/download/7.17/QSVEncC_7.17_x64.7z",
            "hash": "0aea7cf73c051d312913370dae7958e76d8b07b54d4e972dd0261ca58255e5ab",
            "bin": [
                [
                    "QSVEncC64.exe",
                    "qsvencc"
                ]
            ]
        }
    },
    "checkver": "github",
    "autoupdate": {
        "architecture": {
            "32bit": {
                "url": "https://github.com/rigaya/QSVEnc/releases/download/$version/QSVEncC_$version_Win32.7z"
            },
            "64bit": {
                "url": "https://github.com/rigaya/QSVEnc/releases/download/$version/QSVEncC_$version_x64.7z"
            }
        }
    }
}
