{
    "homepage": "https://github.com/rigaya/QSVEnc",
    "description": "Transcoding software using Intel Quick Sync Video.",
    "version": "7.16",
    "license": "MIT",
    "architecture": {
        "32bit": {
            "url": "https://github.com/rigaya/QSVEnc/releases/download/7.16/QSVEncC_7.16_Win32.7z",
            "hash": "9af5b89711ca6f43929c5d45875212e2de0de86b258479a81d859aa4a5ed9ff8",
            "bin": [
                [
                    "QSVEncC.exe",
                    "qsvencc"
                ]
            ]
        },
        "64bit": {
            "url": "https://github.com/rigaya/QSVEnc/releases/download/7.16/QSVEncC_7.16_x64.7z",
            "hash": "ac28e9983d1e7b12e7f172f3625d135560b706243251d08bf9ff0232219bc82c",
            "bin": [
                [
                    "QSVEncC64.exe",
                    "qsvencc"
                ]
            ]
        }
    },
    "checkver": "github",
    "autoupdate": {
        "architecture": {
            "32bit": {
                "url": "https://github.com/rigaya/QSVEnc/releases/download/$version/QSVEncC_$version_Win32.7z"
            },
            "64bit": {
                "url": "https://github.com/rigaya/QSVEnc/releases/download/$version/QSVEncC_$version_x64.7z"
            }
        }
    }
}
